omxpy/__init__.py
omxpy/base_client.py
omxpy/contracts/__init__.py
omxpy/contracts/omx_cw_base_token/__init__.py
omxpy/contracts/omx_cw_bonus_distributor/__init__.py
omxpy/contracts/omx_cw_olp_manager/__init__.py
omxpy/contracts/omx_cw_orderbook/__init__.py
omxpy/contracts/omx_cw_pair/__init__.py
omxpy/contracts/omx_cw_reward_distributor/__init__.py
omxpy/contracts/omx_cw_reward_router/__init__.py
omxpy/contracts/omx_cw_reward_tracker/__init__.py
omxpy/contracts/omx_cw_router/__init__.py
omxpy/contracts/omx_cw_shorts_tracker/__init__.py
omxpy/contracts/omx_cw_staked_olp/__init__.py
omxpy/contracts/omx_cw_vault/__init__.py
omxpy/contracts/omx_cw_vault_price_feed/__init__.py
omxpy/contracts/omx_cw_vester/__init__.py
omxpy/contracts/omx_cw_wrapped_token/__init__.py
omxpy-0.0.12.dist-info/LICENSE
omxpy-0.0.12.dist-info/METADATA
omxpy-0.0.12.dist-info/WHEEL
omxpy-0.0.12.dist-info/RECORD
