Metadata-Version: 2.1
Name: omxpy
Version: 0.0.12
Summary: 
License: MIT
Author: Omx
Author-email: omxlabs@gmail.com
Requires-Python: >=3.10,<3.12
Classifier: License :: OSI Approved :: MIT License
Classifier: Programming Language :: Python :: 3
Classifier: Programming Language :: Python :: 3.10
Classifier: Programming Language :: Python :: 3.11
Requires-Dist: cosmpy (>=0.8.0,<0.9.0)
